partd/__init__.py
partd/_version.py
partd/buffer.py
partd/compressed.py
partd/core.py
partd/dict.py
partd/encode.py
partd/file.py
partd/numpy.py
partd/pandas.py
partd/pickle.py
partd/python.py
partd/utils.py
partd/zmq.py
partd-1.4.1.dist-info/LICENSE.txt
partd-1.4.1.dist-info/METADATA
partd-1.4.1.dist-info/WHEEL
partd-1.4.1.dist-info/top_level.txt
partd-1.4.1.dist-info/RECORD
