Metadata-Version: 2.1
Name: partd
Version: 1.4.1
Summary: Appendable key-value storage
Home-page: http://github.com/dask/partd/
Maintainer: Matthew Rocklin
Maintainer-email: mrocklin@gmail.com
License: BSD
Classifier: Programming Language :: Python :: 3
Classifier: Programming Language :: Python :: 3.7
Classifier: Programming Language :: Python :: 3.8
Classifier: Programming Language :: Python :: 3.9
Classifier: Programming Language :: Python :: 3.10
Classifier: Programming Language :: Python :: 3.11
Requires-Python: >=3.7
Provides-Extra: complete
License-File: LICENSE.txt
